removinator/__init__.py
removinator/removinator.py
removinator-0.1.0.dev3.dist-info/METADATA
removinator-0.1.0.dev3.dist-info/WHEEL
removinator-0.1.0.dev3.dist-info/top_level.txt
removinator-0.1.0.dev3.dist-info/RECORD
