Metadata-Version: 2.1
Name: removinator
Version: 0.1.0.dev3
Summary: A library for controlling the Smart Card Removinator
Home-page: https://github.com/nkinder/smart-card-removinator
Author: Smart Card Removinator contributors
Author-email: nkinder@redhat.com
License: APLv2
Platform: UNKNOWN
Classifier: Intended Audience :: Developers
Classifier: Topic :: Software Development :: Testing
Classifier: Topic :: Software Development :: Libraries :: Python Modules
Classifier: Programming Language :: Python :: 2.7
Classifier: Programming Language :: Python :: 3.4
Classifier: Programming Language :: Python :: 3.5
Requires-Dist: pyserial
